databricks/_feature_store_pkg_metadata/__init__.py
databricks/_feature_store_pkg_metadata/_lookup_client_pkg_metadata/__init__.py
databricks/feature_store/__init__.py
databricks/feature_store/feature_lookup_version.py
databricks/feature_store/mlflow_model.py
databricks/feature_store/online_lookup_client.py
databricks/feature_store/postgres_fetcher.py
databricks/feature_store/entities/feature_functions_for_serving.py
databricks/feature_store/entities/feature_table_metadata.py
databricks/feature_store/feature_functions/feature_function_executor.py
databricks/feature_store/feature_functions/feature_function_loader.py
databricks/feature_store/feature_functions/utils/__init__.py
databricks/feature_store/feature_functions/utils/codegen_utils.py
databricks/feature_store/lookup_engine/__init__.py
databricks/feature_store/lookup_engine/async_refill_engine.py
databricks/feature_store/lookup_engine/lookup_cosmosdb_engine.py
databricks/feature_store/lookup_engine/lookup_dynamodb_engine.py
databricks/feature_store/lookup_engine/lookup_engine.py
databricks/feature_store/lookup_engine/lookup_lakebase_engine.py
databricks/feature_store/lookup_engine/lookup_legacy_brickstore_http_engine.py
databricks/feature_store/lookup_engine/lookup_mysql_engine.py
databricks/feature_store/lookup_engine/lookup_sql_engine.py
databricks/feature_store/lookup_engine/lookup_sql_server_engine.py
databricks/feature_store/lookup_engine/oauth_token_manager.py
databricks/feature_store/metrics/__init__.py
databricks/feature_store/metrics/feature_store_metrics_recorder.py
databricks/feature_store/metrics/metrics_recorder_interface.py
databricks/feature_store/utils/brickstore_http_type_utils.py
databricks/feature_store/utils/collection_utils.py
databricks/feature_store/utils/cosmosdb_type_utils.py
databricks/feature_store/utils/cosmosdb_utils.py
databricks/feature_store/utils/data_type_details_utils.py
databricks/feature_store/utils/delta_sharing_utils.py
databricks/feature_store/utils/dynamodb_type_utils.py
databricks_feature_lookup-1.11.0.dist-info/licenses/LICENSE.md
databricks_feature_lookup-1.11.0.dist-info/licenses/NOTICE.md
databricks_feature_lookup-1.11.0.dist-info/METADATA
databricks_feature_lookup-1.11.0.dist-info/WHEEL
databricks_feature_lookup-1.11.0.dist-info/top_level.txt
databricks_feature_lookup-1.11.0.dist-info/RECORD
