Metadata-Version: 2.4
Name: databricks-feature-lookup
Version: 1.11.0
Summary: Databricks Feature Store Feature Lookup Client
Author: Databricks
Author-email: feedback@databricks.com
License: Databricks Proprietary License
Classifier: Development Status :: 5 - Production/Stable
Classifier: License :: Other/Proprietary License
Classifier: Programming Language :: Python :: 3.7
Classifier: Programming Language :: Python :: 3.8
Classifier: Programming Language :: Python :: 3.9
Classifier: Programming Language :: Python :: Implementation :: CPython
Classifier: Programming Language :: Python :: Implementation :: PyPy
Requires-Python: >=3.7
License-File: LICENSE.md
License-File: NOTICE.md
Requires-Dist: mlflow<4,>=2.16.0
Requires-Dist: pyyaml>=5.1
Requires-Dist: sqlalchemy>=1.4.8
Requires-Dist: pymysql>=1.0.2
Requires-Dist: boto3>=1.19.9
Requires-Dist: azure-cosmos>=4.2.0
Requires-Dist: psycopg[binary]>=3.1
Requires-Dist: protobuf<7,>=5
Requires-Dist: pyarrow>=16
Requires-Dist: requests==2.*
Requires-Dist: numpy<3
Requires-Dist: PyJWT[crypto]>=2
Dynamic: author
Dynamic: author-email
Dynamic: classifier
Dynamic: description
Dynamic: description-content-type
Dynamic: license
Dynamic: license-file
Dynamic: requires-dist
Dynamic: requires-python
Dynamic: summary
